Serialization504/Fabric_for_serialise.py
Serialization504/Json_serialiser.py
Serialization504/Xml_serialiser.py
Serialization504/__init__.py
Serialization504/const.py
Serialization504/serialiser.py
Serialization504-0.1.0.dist-info/METADATA
Serialization504-0.1.0.dist-info/WHEEL
Serialization504-0.1.0.dist-info/top_level.txt
Serialization504-0.1.0.dist-info/RECORD
